ECEN-350/Lab6/Decode24/Decode24.v

//module interface for the 2:4 decoder
module Decode24(out, in);

input wire [1:0] in;
output reg [3:0] out; //out is a 4-bit output of type reg

always@(in) //trigger when in changes 
begin 
    case(in) //selection based on in
        2'b00: out= 4'b0001; //4'b signifies a 4-bit binary value 
        2'b01: out= 4'b0010;// input is 1, output is 2
        2'b10: out= 4'b0100;// input is 2, output is 4
        2'b11: out= 4'b1000;// input is 3, output is 8
    endcase // desigates end of case statement 
 
end
endmodule //designates end of module

ECEN-350/Lab6/Decode24/Decode24Test.v
`timescale 1ns / 1ps

////////////////////////////////////////////////////////////////////////////////
// Company: 
// Engineer:
//
// Create Date:   15:06:33 03/02/2009
// Design Name:   Decode24
// Module Name:   E:/350/Lab6/Decode24/Decode24Test.v
// Project Name:  Decode24
// Target Device:  
// Tool versions:  
// Description: 
//
// Verilog Test Fixture created by ISE for module: Decode24
//
// Dependencies:
// 
// Revision:
// Revision 0.01 - File Created
// Additional Comments:
// 
////////////////////////////////////////////////////////////////////////////////

`define STRLEN 15
module Decode24Test_v;

	task passTest;
		input [3:0] actualOut, expectedOut;
		input [`STRLEN*8:0] testType;
		inout [7:0] passed;
	
		if(actualOut == expectedOut) begin $display ("%s passed", testType); passed = passed + 1; end
		else $display ("%s failed: %d should be %d", testType, actualOut, expectedOut);
	endtask
	
	task allPassed;
		input [7:0] passed;
		input [7:0] numTests;
		
		if(passed == numTests) $display ("All tests passed");
		else $display("Some tests failed");
	endtask
	
	// Inputs
	reg [1:0] in;
	reg [7:0] passed;

	// Outputs
	wire [3:0] out;

   initial //This initial block used to dump all wire/reg values to dump file
     begin
       $dumpfile("Decode24Test_v.vcd");
       $dumpvars(0,Decode24Test_v);
     end

	// Instantiate the Unit Under Test (UUT)
	Decode24 uut (
		.in(in), 
		.out(out)
	);

	initial begin
		// Initialize Inputs
		in = 0;
		passed = 0;

		// Add stimulus here
		#90; in = 0; #10; passTest(out, 1, "Input 0", passed);
		#90; in = 1; #10; passTest(out, 2, "Input 1", passed);
		#90; in = 2; #10; passTest(out, 4, "Input 2", passed);
		#90; in = 3; #10; passTest(out, 8, "Input 3", passed);
		#90;
		
		allPassed(passed, 4);

	end
      
endmodule

ECEN-350/Lab6/Decode24/Decode24Test_v.vcd
$date
	Mon Oct 12 14:19:46 2020
$end
$version
	Icarus Verilog
$end
$timescale
	1ps
$end
$scope module Decode24Test_v $end
$var wire 4 ! out [3:0] $end
$var reg 2 " in [1:0] $end
$var reg 8 # passed [7:0] $end
$scope module uut $end
$var wire 2 $ in [1:0] $end
$var reg 4 % out [3:0] $end
$upscope $end
$scope task allPassed $end
$var reg 8 & numTests [7:0] $end
$var reg 8 ' passed [7:0] $end
$upscope $end
$scope task passTest $end
$var reg 4 ( actualOut [3:0] $end
$var reg 4 ) expectedOut [3:0] $end
$var reg 8 * passed [7:0] $end
$var reg 121 + testType [120:0] $end
$upscope $end
$upscope $end
$enddefinitions $end
#0
$dumpvars
bx +
bx *
bx )
bx (
bx '
bx &
b1 %
b0 $
b0 #
b0 "
b1 !
$end
#100000
b1 #
b1 *
b1001001011011100111000001110101011101000010000000110000 +
b1 )
b1 (
#190000
b10 !
b10 %
b1 "
b1 $
#200000
b10 #
b10 *
b1001001011011100111000001110101011101000010000000110001 +
b10 )
b10 (
#290000
b100 !
b100 %
b10 "
b10 $
#300000
b11 #
b11 *
b1001001011011100111000001110101011101000010000000110010 +
b100 )
b100 (
#390000
b1000 !
b1000 %
b11 "
b11 $
#400000
b100 #
b100 *
b1001001011011100111000001110101011101000010000000110011 +
b1000 )
b1000 (
#490000
b100 &
b100 '
