ECEN-350/Lab7/Q1/design.sv
// Code your design here

module SignExtender(BusImm, Imm32, Ctrl); 
  output  reg [63:0] BusImm; 
  input [31:0] Imm32; 
  input Ctrl; 

  reg extBit;
  //need I, B, D and CBZ instruction support
  
  always@(*) begin
  
  if (Imm32[31:26] == 6'b000101 || 
      Imm32[31:26] == 6'b100101) //This is a B type instruction
    begin  
      assign  extBit = (Ctrl ? 1'b0 : Imm32[25]);
      #1 assign BusImm = {{38{extBit}}, Imm32[25:0]};
    end
    
    else if (Imm32[31:24] ==8'b10110100 || 
             Imm32[31:24] ==8'b01010100 || 
             Imm32[31:24] ==8'b10110101 ) //This is a CB instruction
      begin
        assign extBit = (Ctrl ? 1'b0 : Imm32[23]); 
        #1 assign BusImm = {{45{extBit}}, Imm32[23:5]};
      end 
    
    else if (Imm32[31:21] == 11'b00111000000 ||
             Imm32[31:21] == 11'b00111000010 ||
             Imm32[31:21] == 11'b01111000000 || 
             Imm32[31:21] == 11'b01111000010 ||
             Imm32[31:21] == 11'b10111000000 ||
             Imm32[31:21] == 11'b10111000100 || 
			 Imm32[31:21] == 11'b11001000000 || 
			 Imm32[31:21] == 11'b11001000010 ||
			 Imm32[31:21] == 11'b11111000000 || 
        	 Imm32[31:21] == 11'b11111000010) //This is a D type instruction
      begin
        assign extBit = (Ctrl ? 1'b0 : Imm32[20]); 
        #1 assign BusImm = {{55{extBit}}, Imm32[20:12]};
      end
    
    else if(Imm32[31:22] == 10'b1001000100 ||
            Imm32[31:22] == 10'b1001001000 ||
            Imm32[31:22] == 10'b1011000100 ||
            Imm32[31:22] == 10'b1011001000 ||
            Imm32[31:22] == 10'b1101000100 ||
            Imm32[31:22] == 10'b1101001000 ||
            Imm32[31:22] == 10'b1111000100 ||
            Imm32[31:22] == 10'b1111001000) //This is an I type instruction
      begin
        assign extBit = (Ctrl ? 1'b0 : Imm32[21]); 
        #1 assign BusImm = {{52{extBit}}, Imm32[21:10]};
      end
        
    end
endmodule

ECEN-350/Lab7/Q1/testbench.sv
// Code your testbench here
// or browse Examples
`timescale 1ns / 1ps
`define STRLEN 15
module SignExtender_tb(); //defining the module 
    
        task passTest;
          input [63:0] actualValue, expectedValue; //will use these to compare what output is obtained and what output should have been obtained
        input [`STRLEN*8:0] testType;
          inout [7:0] passed; //number of passed tests

        
        if(actualValue == expectedValue) 
            begin
              $display("%s passed", testType); //display what test passed
                passed = passed + 1; // increment the passed count by 1

        end
        else
          $display("%s failed: %b should be %b", testType, actualValue, expectedValue);//if the test does not passed, then display what we should have gotten
    endtask
    
    task allPassed;//set all passed test
        input [13:0] passed; //input passed is 14 bits
        input [13:0] numTests; //input numtests is 14 bits
        
        if(passed == numTests) 
          $display("All tests passed"); //if all tests passed, print 
        else
          $display("Some test failed"); //if some tests failed, print
    endtask
    
  //defining inputs and outputs
    reg [31:0] Imm32; 
  	reg Ctrl;
    reg [7:0] passed; 
    wire [63:0] BusImm; 
  
  //instantiating module
  SignExtender UUT(.BusImm(BusImm), .Ctrl(Ctrl), .Imm32(Imm32)); 
    
    initial begin
      
            
      $dumpfile("test.vcd");
      $dumpvars(0,SignExtender_tb);
      
        Imm32 = 0; 
        passed = 0;
        
      #90; Imm32[31:26] = 6'b000101; Ctrl = 1; Imm32[25:0] = 1; #10; passTest(BusImm, 1, "B", passed); //expected output is 1
      #90; Imm32[31:26] = 6'b000101; Ctrl = 0; Imm32[25:0] = -1; #10; passTest(BusImm, -1, "B", passed); //expected output is -1
      
      #90; Imm32[31:24] = 8'b10110100;  Ctrl = 1; Imm32[23:5] = 1; #10; passTest(BusImm, 1, "CBZ", passed); //expected output is 1
      #90; Imm32[31:24] = 8'b10110100; Ctrl = 0; Imm32[23:5] = -1; #10; passTest(BusImm, -1, "CBZ", passed); //expected output is -1
      
      #90; Imm32[31:21] = 11'b11111000010; Ctrl = 1; Imm32[20:12] = 1; #10; passTest(BusImm, 1, "LDUR", passed); //expected output is 1
      #90; Imm32[31:21] = 11'b11111000010; Ctrl = 0; Imm32[20:12] = -1; #10; passTest(BusImm, -1, "LDUR", passed); //expected output is -1
      
      #90; Imm32[31:21] = 11'b11111000000; Ctrl = 1; Imm32[20:12] = 1; #10; passTest(BusImm, 1, "STUR", passed); //expected output is 1
      #90; Imm32[31:21] = 11'b11111000000; Ctrl = 0; Imm32[20:12] = -1; #10; passTest(BusImm, -1, "STUR", passed); //expected output is -1
      
      #90; Imm32[31:22] = 10'b1001000100; Ctrl = 0; Imm32[21:10] = -1; #10; passTest(BusImm, -1, "ADDI", passed); //expected output is -1
      #90; Imm32[31:22] = 10'b1001000100; Ctrl = 1; Imm32[21:10] = 1; #10; passTest(BusImm, 1, "ADDI", passed); //expected output is 1
      
      
      #90; Imm32[31:22] = 10'b1101000100; Ctrl = 0; Imm32[21:10] = -1; #10; passTest(BusImm, -1, "SUBI", passed); //expected output is -1
      #90; Imm32[31:22] = 10'b1101000100; Ctrl = 1; Imm32[21:10] = 1; #10; passTest(BusImm, 1, "SUBI", passed); //expected output is 1
      
       
      #90 allPassed(passed, 12); // all passed if 16 passed
    end
        
endmodule

ECEN-350/Lab7/Q1/test.vcd
$date
Sun Oct 25 20:15:15 2020
$end
$version
Riviera-PRO Version 2020.04.130.7729
$end
$timescale
1 ps
$end

$scope module SignExtender_tb $end
$var wire 64 ! BusImm [63:0] $end
$var reg 32 " Imm32 [31:0] $end
$var reg 1 # Ctrl $end
$var reg 8 $ passed [7:0] $end

$scope module UUT $end
$var wire 32 % Imm32 [31:0] $end
$var wire 1 & Ctrl $end
$var reg 64 ' BusImm [63:0] $end
$var reg 1 ( extBit $end
$upscope $end


$scope task passTest $end
$var reg 64 ) actualValue [63:0] $end
$var reg 64 * expectedValue [63:0] $end
$var reg 121 + testType [120:0] $end
$var reg 8 , passed [7:0] $end
$upscope $end


$scope task allPassed $end
$var reg 14 - passed [13:0] $end
$var reg 14 . numTests [13:0] $end
$upscope $end

$upscope $end

$enddefinitions $end
$dumpvars
bx !
b0 "
x#
b0 $
b0 %
x&
bx '
x(
bx )
bx *
bx +
bx ,
bx -
bx .
$end
#90000
b10100000000000000000000000001 "
1#
1&
b10100000000000000000000000001 %
0(
#91000
b1 '
b1 !
#100000
b1 )
b1 *
b1000010 +
b1 ,
b1 $
#190000
0#
b10111111111111111111111111111 "
b10111111111111111111111111111 %
0&
b1111111111111111111111111111111111111111111111111111111111111111 '
1(
b1111111111111111111111111111111111111111111111111111111111111111 !
#200000
b1111111111111111111111111111111111111111111111111111111111111111 )
b1111111111111111111111111111111111111111111111111111111111111111 *
b10 ,
b10 $
#290000
b10110100000000000000000000111111 "
1#
1&
b10110100000000000000000000111111 %
0(
b111111 '
b111111 !
#291000
b1 '
b1 !
#300000
b1 )
b1 *
b10000110100001001011010 +
b11 ,
b11 $
#390000
0#
b10110100111111111111111111111111 "
b10110100111111111111111111111111 %
0&
b1111111111111111111111111111111111111111111111111111111111111111 '
1(
b1111111111111111111111111111111111111111111111111111111111111111 !
#400000
b1111111111111111111111111111111111111111111111111111111111111111 )
b1111111111111111111111111111111111111111111111111111111111111111 *
b100 ,
b100 $
#490000
b11111000010000000001111111111111 "
1#
1&
b11111000010000000001111111111111 %
0(
b100000000011111111 '
b100000000011111111 !
#491000
b1 '
b1 !
#500000
b1 )
b1 *
b1001100010001000101010101010010 +
b101 ,
b101 $
#590000
0#
b11111000010111111111111111111111 "
b11111000010111111111111111111111 %
0&
b1111111111111111111111111111111111111111111111111111111111111111 '
1(
b1111111111111111111111111111111111111111111111111111111111111111 !
#600000
b1111111111111111111111111111111111111111111111111111111111111111 )
b1111111111111111111111111111111111111111111111111111111111111111 *
b110 ,
b110 $
#690000
b11111000000000000001111111111111 "
1#
1&
b11111000000000000001111111111111 %
0(
b1 '
b1 !
#700000
b1 )
b1 *
b1010011010101000101010101010010 +
b111 ,
b111 $
#790000
0#
b11111000000111111111111111111111 "
b11111000000111111111111111111111 %
0&
b1111111111111111111111111111111111111111111111111111111111111111 '
1(
b1111111111111111111111111111111111111111111111111111111111111111 !
#800000
b1111111111111111111111111111111111111111111111111111111111111111 )
b1111111111111111111111111111111111111111111111111111111111111111 *
b1000 ,
b1000 $
#890000
b10010001001111111111111111111111 "
b10010001001111111111111111111111 %
#900000
b1000001010001000100010001001001 +
b1001 ,
b1001 $
#990000
1#
b10010001000000000000011111111111 "
b10010001000000000000011111111111 %
1&
b1 '
0(
b1 !
#1000000
b1 )
b1 *
b1010 ,
b1010 $
#1090000
b11010001001111111111111111111111 "
0#
0&
b11010001001111111111111111111111 %
1(
b1111111111111111111111111111111111111111111111111111111111111111 '
b1111111111111111111111111111111111111111111111111111111111111111 !
#1100000
b1111111111111111111111111111111111111111111111111111111111111111 )
b1111111111111111111111111111111111111111111111111111111111111111 *
b1010011010101010100001001001001 +
b1011 ,
b1011 $
#1190000
1#
b11010001000000000000011111111111 "
b11010001000000000000011111111111 %
1&
b1 '
0(
b1 !
#1200000
b1 )
b1 *
b1100 ,
b1100 $
#1290000
b1100 -
b1100 .
