ECEN-350/Lab7/Q2/design.sv
// Code your design here
`timescale 1ns / 1ps

module ALU(BusW, Zero , BusA , BusB , ALUCtrl );
  
  //declare inputs and outputs
  input [63:0] BusA, BusB;
  input [3:0] ALUCtrl;
  output [63:0] BusW;
  output Zero;
  
  reg [63:0] BusW;
  reg Zero;
  
  always@(ALUCtrl or BusA or BusB)
    begin
      case(ALUCtrl)
        4'b0000: //AND
          BusW <= #20 BusA & BusB;
        4'b0001: //OR
          BusW <= #20 BusA | BusB;
        4'b0010: //ADD
          BusW <= #20 BusA + BusB;
        4'b0110: //SUB
          BusW <= #20 BusA - BusB;
         4'b0111: //PASSB
          BusW <= #20 BusB;
      endcase
     end
        
 always@(BusW)
   begin
     if(BusW == 0) 
          Zero <= 1;
     else
          Zero <= 0;
       
    end
     
        
endmodule

ECEN-350/Lab7/Q2/testbench.sv
// Code your testbench here
// or browse Examples
//`timescale 1ns / 1ps

////////////////////////////////////////////////////////////////////////////////
// Company: 
// Engineer:
//
// Create Date:   10:02:47 03/05/2009
// Design Name:   ALU
// Module Name:   E:/350/Lab8/ALU/ALUTest.v
// Project Name:  ALU
// Target Device:  
// Tool versions:  
// Description: 
//
// Verilog Test Fixture created by ISE for module: ALU
//
// Dependencies:
// 
// Revision:
// Revision 0.01 - File Created
// Additional Comments:
// 
////////////////////////////////////////////////////////////////////////////////
//`timescale 1ns / 1ps
`define STRLEN 32
module ALUTest_v;

	task passTest;
		input [64:0] actualOut, expectedOut;
		input [`STRLEN*8:0] testType;
		inout [7:0] passed;
	
		if(actualOut == expectedOut) begin $display ("%s passed", testType); passed = passed + 1; end
		else $display ("%s failed: %x should be %x", testType, actualOut, expectedOut);
	endtask
	
	task allPassed;
		input [7:0] passed;
		input [7:0] numTests;
		
		if(passed == numTests) $display ("All tests passed");
		else $display("Some tests failed");
	endtask

	// Inputs
	reg [63:0] BusA;
	reg [63:0] BusB;
	reg [3:0] ALUCtrl;
	reg [7:0] passed;

	// Outputs
	wire [63:0] BusW;
	wire Zero;

	// Instantiate the Unit Under Test (UUT)
	ALU uut (
		.BusW(BusW), 
		.Zero(Zero), 
		.BusA(BusA), 
		.BusB(BusB), 
		.ALUCtrl(ALUCtrl)
	);

	initial begin
      $dumpfile("test.vcd");
      $dumpvars(0,ALUTest_v);
      
		// Initialize Inputs
		BusA = 0;
		BusB = 0;
		ALUCtrl = 0;
		passed = 0;

                // Here is one example test vector, testing the ADD instruction:
      //{BusA, BusB, ALUCtrl} = {64'h1234, 64'hABCD0000, 4'h2}; #40; passTest({Zero, BusW}, 65'h0ABCD1234, "ADD 0x1234,0xABCD0000", passed);
		//Reformate and add your test vectors from the prelab here following the example of the testvector above.	
      
      {BusA, BusB, ALUCtrl} = {64'h1, 64'h8, 4'h0}; #40; passTest({Zero, BusW}, 65'h10000000000000000, "AND 0x1,0x8", passed);
      {BusA, BusB, ALUCtrl} = {64'h2, 64'h3, 4'h0}; #40; passTest({Zero, BusW}, 65'h2, "AND 0x2,0x3", passed);
      {BusA, BusB, ALUCtrl} = {64'h5, 64'h1, 4'h0}; #40; passTest({Zero, BusW}, 65'h1, "AND 0x5,0x1", passed);
      
      {BusA, BusB, ALUCtrl} = {64'h4, 64'h6, 4'h1}; #40; passTest({Zero, BusW}, 65'h6, "OR 0x4,0x6", passed);
      {BusA, BusB, ALUCtrl} = {64'h7, 64'h3, 4'h1}; #40; passTest({Zero, BusW}, 65'h7, "OR 0x7,0x3", passed);
      {BusA, BusB, ALUCtrl} = {64'h3, 64'h8, 4'h1}; #40; passTest({Zero, BusW}, 65'hB, "OR 0x3,0x8", passed);
      
      {BusA, BusB, ALUCtrl} = {64'h1, 64'h9, 4'h2}; #40; passTest({Zero, BusW}, 65'hA, "ADD 0x1,0x9", passed);
      {BusA, BusB, ALUCtrl} = {64'h0, 64'h0, 4'h2}; #40; passTest({Zero, BusW}, 65'h10000000000000000, "ADD 0x0,0x0", passed);
      {BusA, BusB, ALUCtrl} = {64'h7, 64'h1, 4'h2}; #40; passTest({Zero, BusW}, 65'h8, "ADD 0x7,0x1", passed);
      
      {BusA, BusB, ALUCtrl} = {64'hA, 64'h3, 4'h6}; #40; passTest({Zero, BusW}, 65'h7, "SUB 0xA,0x3", passed);
      {BusA, BusB, ALUCtrl} = {64'hB, 64'h2, 4'h6}; #40; passTest({Zero, BusW}, 65'h9, "SUB 0xB,0x2", passed);
      {BusA, BusB, ALUCtrl} = {64'h4, 64'h0, 4'h6}; #40; passTest({Zero, BusW}, 65'h4, "SUB 0x4,0x0", passed);
      
      {BusA, BusB, ALUCtrl} = {64'h1, 64'h6, 4'h7}; #40; passTest({Zero, BusW}, 65'h6, "PASSB 0x1,0x6", passed);
      {BusA, BusB, ALUCtrl} = {64'h2, 64'h6, 4'h7}; #40; passTest({Zero, BusW}, 65'h6, "PASSB 0x1,0x6", passed);
      {BusA, BusB, ALUCtrl} = {64'h3, 64'h6, 4'h7}; #40; passTest({Zero, BusW}, 65'h6, "PASSB 0x1,0x6", passed);
      
      


      allPassed(passed, 15);//22
	end
      
endmodule

ECEN-350/Lab7/Q2/test.vcd
$date
Sun Oct 25 22:50:22 2020
$end
$version
Riviera-PRO Version 2020.04.130.7729
$end
$timescale
1 ps
$end

$scope module ALUTest_v $end
$var wire 64 ! BusW [63:0] $end
$var wire 1 " Zero $end
$var reg 64 # BusA [63:0] $end
$var reg 64 $ BusB [63:0] $end
$var reg 4 % ALUCtrl [3:0] $end
$var reg 8 & passed [7:0] $end

$scope module uut $end
$var wire 64 ' BusA [63:0] $end
$var wire 64 ( BusB [63:0] $end
$var wire 4 ) ALUCtrl [3:0] $end
$var reg 64 * BusW [63:0] $end
$var reg 1 + Zero $end
$upscope $end


$scope task passTest $end
$var reg 65 , actualOut [64:0] $end
$var reg 65 - expectedOut [64:0] $end
$var reg 257 . testType [256:0] $end
$var reg 8 / passed [7:0] $end
$upscope $end


$scope task allPassed $end
$var reg 8 0 passed [7:0] $end
$var reg 8 1 numTests [7:0] $end
$upscope $end

$upscope $end

$enddefinitions $end
$dumpvars
bx !
x"
b1 #
b1000 $
b0 %
b0 &
b1 '
b1000 (
b0 )
bx *
x+
bx ,
bx -
bx .
bx /
bx 0
bx 1
$end
#20000
b0 *
b0 !
1+
1"
#40000
b10000000000000000000000000000000000000000000000000000000000000000 ,
b10000000000000000000000000000000000000000000000000000000000000000 -
b100000101001110010001000010000000110000011110000011000100101100001100000111100000111000 .
b1 /
b1 &
b11 $
b10 #
b10 '
b11 (
#60000
b10 *
b10 !
0+
0"
#80000
b10 ,
b10 -
b100000101001110010001000010000000110000011110000011001000101100001100000111100000110011 .
b10 /
b10 &
b1 $
b101 #
b101 '
b1 (
#100000
b1 *
b1 !
#120000
b1 ,
b1 -
b100000101001110010001000010000000110000011110000011010100101100001100000111100000110001 .
b11 /
b11 &
b1 %
b110 $
b100 #
b100 '
b110 (
b1 )
#140000
b110 *
b110 !
#160000
b110 ,
b110 -
b1001111010100100010000000110000011110000011010000101100001100000111100000110110 .
b100 /
b100 &
b11 $
b111 #
b111 '
b11 (
#180000
b111 *
b111 !
#200000
b111 ,
b111 -
b1001111010100100010000000110000011110000011011100101100001100000111100000110011 .
b101 /
b101 &
b1000 $
b11 #
b11 '
b1000 (
#220000
b1011 *
b1011 !
#240000
b1011 ,
b1011 -
b1001111010100100010000000110000011110000011001100101100001100000111100000111000 .
b110 /
b110 &
b10 %
b1001 $
b1 #
b1 '
b1001 (
b10 )
#260000
b1010 *
b1010 !
#280000
b1010 ,
b1010 -
b100000101000100010001000010000000110000011110000011000100101100001100000111100000111001 .
b111 /
b111 &
b0 $
b0 #
b0 '
b0 (
#300000
b0 *
b0 !
1+
1"
#320000
b10000000000000000000000000000000000000000000000000000000000000000 ,
b10000000000000000000000000000000000000000000000000000000000000000 -
b100000101000100010001000010000000110000011110000011000000101100001100000111100000110000 .
b1000 /
b1000 &
b1 $
b111 #
b111 '
b1 (
#340000
b1000 *
b1000 !
0+
0"
#360000
b1000 ,
b1000 -
b100000101000100010001000010000000110000011110000011011100101100001100000111100000110001 .
b1001 /
b1001 &
b110 %
b11 $
b1010 #
b1010 '
b11 (
b110 )
#380000
b111 *
b111 !
#400000
b111 ,
b111 -
b101001101010101010000100010000000110000011110000100000100101100001100000111100000110011 .
b1010 /
b1010 &
b10 $
b1011 #
b1011 '
b10 (
#420000
b1001 *
b1001 !
#440000
b1001 ,
b1001 -
b101001101010101010000100010000000110000011110000100001000101100001100000111100000110010 .
b1011 /
b1011 &
b0 $
b100 #
b100 '
b0 (
#460000
b100 *
b100 !
#480000
b100 ,
b100 -
b101001101010101010000100010000000110000011110000011010000101100001100000111100000110000 .
b1100 /
b1100 &
b111 %
b110 $
b1 #
b1 '
b110 (
b111 )
#500000
b110 *
b110 !
#520000
b110 ,
b110 -
b1010000010000010101001101010011010000100010000000110000011110000011000100101100001100000111100000110110 .
b1101 /
b1101 &
b10 #
b10 '
#560000
b1110 /
b1110 &
b11 #
b11 '
#600000
b1111 /
b1111 &
b1111 0
b1111 1
