ECEN-350/Lab9/Part2/DataMemory.v
`timescale 1ns / 1ps

`define SIZE 1024

module DataMemory(ReadData , Address , WriteData , MemoryRead , MemoryWrite , Clock);
    input [63:0]      WriteData;
    input [63:0]      Address;
    input             Clock, MemoryRead, MemoryWrite;
    output reg [63:0] ReadData;

    reg [7:0]         memBank [`SIZE-1:0];


    // This task is used to write arbitrary data to the Data Memory by
    // the intialization block.
    task initset;
      input [63:0] addr;
      input [63:0] data;
      begin
     memBank[addr] =  data[63:56] ; // Big-endian for the win...
     memBank[addr+1] =  data[55:48];
     memBank[addr+2] =  data[47:40];
     memBank[addr+3] =  data[39:32];
     memBank[addr+4] =  data[31:24];
     memBank[addr+5] =  data[23:16];
     memBank[addr+6] =  data[15:8];
     memBank[addr+7] =  data[7:0];
      end
    endtask


    initial
    begin
        // preseting some data in the data memory used by test #1

        // Address 0x0 gets 0x1
        initset( 64'h0,  64'h1);  //Counter variable
        initset( 64'h8,  64'ha);  //Part of mask
        initset( 64'h10, 64'h5);  //Other part of mask
        initset( 64'h18, 64'h0ffbea7deadbeeff); //big constant
        initset( 64'h20, 64'h0); //clearing space

        // Add any data you need for your tests here.

    end

    // This always block reads the data memory and places a double word
    // on the ReadData bus.
    always @(posedge Clock)
    begin
        if(MemoryRead)
        begin
            ReadData[63:56] <= #20 memBank[Address];
            ReadData[55:48] <= #20 memBank[Address+1];
            ReadData[47:40] <= #20 memBank[Address+2];
            ReadData[39:32] <= #20 memBank[Address+3];
            ReadData[31:24] <= #20 memBank[Address+4];
            ReadData[23:16] <= #20 memBank[Address+5];
            ReadData[15:8] <= #20 memBank[Address+6];
            ReadData[7:0] <= #20 memBank[Address+7];
        end
    end

    // This always block takes data from the WriteData bus and writes
    // it into the DataMemory.
    always @(posedge Clock)
    begin
        if(MemoryWrite)
        begin
            memBank[Address] <= #20 WriteData[63:56] ;
            memBank[Address+1] <= #20 WriteData[55:48];
            memBank[Address+2] <= #20 WriteData[47:40];
            memBank[Address+3] <= #20 WriteData[39:32];
            memBank[Address+4] <= #20 WriteData[31:24];
            memBank[Address+5] <= #20 WriteData[23:16];
            memBank[Address+6] <= #20 WriteData[15:8];
            memBank[Address+7] <= #20 WriteData[7:0];
            // Could be useful for debugging:
            $display("Writing Address:%h Data:%h",Address, WriteData);
        end
    end
endmodule

ECEN-350/Lab9/Part2/RegisterFile.v
`timescale 1ns / 1ps
module RegisterFile(BusA, BusB, BusW, RA, RB, RW, RegWr, Clk);
    output [63:0] BusA;
    output [63:0] BusB;
    input [63:0] BusW;
    input [4:0] RW, RA, RB;//input registers
    input RegWr;
    input Clk;
  	reg [63:0] registers [31:0];
     
  assign #2 BusA = (RA==31)? 64'b0 : registers[RA];//register A gets passed to BusA
  assign #2 BusB = (RB==31)? 64'b0 : registers[RB];
  
     
    /*initial begin
      for(int i = 0; i < 32; i = i + 1) begin //initialize all of the register values to 0
            registers[i] <= 0;
        end
    end*/
  
    always @ (negedge Clk) begin
      registers[31]<= #3 0;  //always have register 31 as 0
      if(RegWr) begin
        if(RW !=31) begin //if not the 31st register, then assign RW with the value of BusW 
            registers[RW] <= #3 BusW;
        end
      end
    end
endmodule

ECEN-350/Lab9/Part1/ALU.v
// Code your design here
`timescale 1ns / 1ps

module ALU(BusW, Zero , BusA , BusB , ALUCtrl );
  
  //declare inputs and outputs
  input [63:0] BusA, BusB;
  input [3:0] ALUCtrl;
  output [63:0] BusW;
  output Zero;
  
  reg [63:0] BusW;
  reg Zero;
  
  always@(ALUCtrl or BusA or BusB)
    begin
      case(ALUCtrl)
        4'b0000: //AND
          BusW <= BusA & BusB;
        4'b0001: //OR
          BusW <= BusA | BusB;
        4'b0010: //ADD
          BusW <=  BusA + BusB;
        4'b0110: //SUB
          BusW <=  BusA - BusB;
         4'b0111: //PASSB
          BusW <=  BusB;
      endcase
     end
        
 always@(BusW)
   begin
     if(BusW == 0) 
          Zero <= 1;
     else
          Zero <= 0;
       
    end
     
        
endmodule

ECEN-350/Lab9/Part1/SignExtender.v
`define Btype 2'b00
`define Itype 2'b01
`define Dtype 2'b10
`define CBZtype 2'b11


module SignExtender(BusImm, Imm26, Ctrl); 
  output  reg [63:0] BusImm; 
  input [25:0] Imm26; 
  input [1:0] Ctrl; 

  reg extBit;
  //need I, B, D and CBZ instruction support
  
  always@(Imm26 or Ctrl) begin
    case(Ctrl)
      `Btype: begin
        extBit = Imm26[25];
        BusImm = {{38{extBit}},Imm26};
      end
      `Itype: begin
        //extBit = Imm26[21];
        BusImm = {{52{1'b0}},Imm26[21:10]};
      end
      `Dtype: begin
        extBit = Imm26[20];
        BusImm = {{55{extBit}},Imm26[20:12]};
      end
      `CBZtype: begin
        extBit = Imm26[23];
        BusImm = {{45{extBit}},Imm26[23:5]};        
      end
    endcase        
  end
  
endmodule

ECEN-350/Lab9/Part1/SingleCycleControl.v
`define OPCODE_ANDREG 11'b?0001010???
`define OPCODE_ORRREG 11'b?0101010???
`define OPCODE_ADDREG 11'b?0?01011???
`define OPCODE_SUBREG 11'b?1?01011???

`define OPCODE_ADDIMM 11'b?0?10001???
`define OPCODE_SUBIMM 11'b?1?10001???

`define OPCODE_MOVZ   11'b110100101??

`define OPCODE_B      11'b?00101?????
`define OPCODE_CBZ    11'b?011010????

`define OPCODE_LDUR   11'b??111000010
`define OPCODE_STUR   11'b??111000000

module control(
    output reg reg2loc,
    output reg alusrc,
    output reg mem2reg,
    output reg regwrite,
    output reg memread,
    output reg memwrite,
    output reg branch,
    output reg uncond_branch,
    output reg [3:0] aluop,
    output reg [1:0] signop,
    input [10:0] opcode
);

  always @(opcode)
begin
    casez (opcode)
      `OPCODE_ANDREG: begin
         reg2loc <= 1'b0;
         alusrc <=  1'b0;
         mem2reg <=  1'b0;
         regwrite <=  1'b1;
         memread <=  1'b0;
         memwrite <=  1'b0;
         branch <=  1'b0;
         uncond_branch <=  1'b0;
         aluop <=  4'b0000;
         signop <=  2'bxx;
      end
      
      `OPCODE_ORRREG: begin
         reg2loc <=  1'b0;
         alusrc <=  1'b0;
         mem2reg <=  1'b0;
         regwrite <=  1'b1;
         memread <=  1'b0;
         memwrite <=  1'b0;
         branch <=  1'b0;
         uncond_branch <=  1'b0;
         aluop <=  4'b0001;
         signop <= 2'bxx;
      end
      
       `OPCODE_ADDREG: begin
         reg2loc <=  1'b0;
         alusrc <=  1'b0;
         mem2reg <=  1'b0;
         regwrite <=  1'b1;
         memread <=  1'b0;
         memwrite <=  1'b0;
         branch <=  1'b0;
         uncond_branch <=  1'b0;
         aluop <=  4'b0010;
         signop <=  2'bxx;      
      end
      
       `OPCODE_SUBREG: begin
         reg2loc <=  1'b0;
         alusrc <=  1'b0;
         mem2reg <=  1'b0;
         regwrite <=  1'b1;
         memread <=  1'b0;
         memwrite <=  1'b0;
         branch <=  1'b0;
         uncond_branch <=  1'b0;
         aluop <=  4'b0110;
         signop <=  2'bxx;
      end
      
       `OPCODE_ADDIMM: begin
		 reg2loc <=  1'b0;
         alusrc <=  1'b0;
         mem2reg <=  1'b0;
         regwrite <=  1'b1;
         memread <=  1'b0;
         memwrite <=  1'b0;
         branch <= 1'b0;
         uncond_branch <=  1'b0;
         aluop <=  4'b0010;
         signop <=  2'b01;
      end
      
       `OPCODE_SUBIMM: begin
         reg2loc <=  1'b0;
         alusrc <=  1'b0;
         mem2reg <=  1'b0;
         regwrite <=  1'b1;
         memread <=  1'b0;
         memwrite <=  1'b0;
         branch <=  1'b0;
         uncond_branch <= 1'b0;
         aluop <=  4'b0110;
         signop <= 2'b01;
  
      end
      
       /*`OPCODE_MOVZ: begin
         reg2loc <= #2
         alusrc <= #2
         mem2reg <= #2
         regwrite <= #2
         memread <= #2
         memwrite <= #2
         branch <= #2
         uncond_branch <= #2
         aluop <= #2
         signop <= #2
      end*/
      
       `OPCODE_B: begin
         reg2loc <=  1'bx;
         alusrc <=  1'bx;
         mem2reg <=  1'bx;
         regwrite <=  1'b0;
         memread <=  1'b0;
         memwrite <=  1'b0;
         branch <=  1'bx;
         uncond_branch <= 1'b1;
         aluop <=  4'bxxxx;
         signop <=  2'b00;
      end
      
       `OPCODE_CBZ: begin
         reg2loc <=  1'b1;
         alusrc <=  1'b0;
         mem2reg <=  1'bx;
         regwrite <=  1'b0;
         memread <=  1'b0;
         memwrite <=  1'b0;
         branch <= 1'b1;
         uncond_branch <=  1'b0;
         aluop <=  4'b0111;
         signop <= 2'b11;
      end
      
       `OPCODE_LDUR: begin
         reg2loc <= 1'bx;
         alusrc <= 1'b1;
         mem2reg <=  1'b1;
         regwrite <= 1'b1;
         memread <= 1'b1;
         memwrite <=  1'b0;
         branch <=  1'b0;
         uncond_branch <=  1'b0;
         aluop <= 4'b0010;
         signop <= 2'b10;
      end
      
       `OPCODE_STUR: begin
         reg2loc <=  1'b1;
         alusrc <=  1'b1;
         mem2reg <=  1'bx; 
         regwrite <=  1'b0;
         memread <=  1'b0;
         memwrite <= 1'b1;
         branch <=  1'b0;
         uncond_branch <=  1'b0;
         aluop <=  4'b0010;
         signop <=  2'b10;
      end
      
      
        

        /* Add cases here for each instruction your processor supports */

        default:
        begin
            reg2loc       <= 1'bx;
            alusrc        <= 1'bx;
            mem2reg       <= 1'bx;
            regwrite      <= 1'b0;
            memread       <= 1'b0;
            memwrite      <= 1'b0;
            branch        <= 1'b0;
            uncond_branch <= 1'b0;
            aluop         <= 4'bxxxx;
            signop        <= 2'bxx;
        end
    endcase
end

endmodule

ECEN-350/Lab9/Part1/InstructionMemory.v
`timescale 1ns / 1ps
/*
 * Module: InstructionMemory
 *
 * Implements read-only instruction memory
 * 
 */
module InstructionMemory(Data, Address);
   parameter T_rd = 20;
   parameter MemSize = 40;
   
   output [31:0] Data;
   input [63:0]  Address;
   reg [31:0] 	 Data;
   
   /*
    * ECEN 350 Processor Test Functions
    * Texas A&M University
    */
   
   always @ (Address) begin
      #4;
      case(Address)

	/* Test Program 1:
	 * Program loads constants from the data memory. Uses these constants to test
	 * the following instructions: LDUR, ORR, AND, CBZ, ADD, SUB, STUR and B.
	 * 
	 * Assembly code for test:
	 * 
	 * 0: LDUR X9, [XZR, 0x0]    //Load 1 into x9
	 * 4: LDUR X10, [XZR, 0x8]   //Load a into x10
	 * 8: LDUR X11, [XZR, 0x10]  //Load 5 into x11
	 * C: LDUR X12, [XZR, 0x18]  //Load big constant into x12
	 * 10: LDUR X13, [XZR, 0x20]  //load a 0 into X13
	 * 
	 * 14: ORR X10, X10, X11  //Create mask of 0xf
	 * 18: AND X12, X12, X10  //Mask off low order bits of big constant
	 * 
	 * loop:
	 * 1C: CBZ X12, end  //while X12 is not 0
	 * 20: ADD X13, X13, X9  //Increment counter in X13
	 * 24: SUB X12, X12, X9  //Decrement remainder of big constant in X12
	 * 28: B loop  //Repeat till X12 is 0
	 * 2C: STUR X13, [XZR, 0x20]  //store back the counter value into the memory location 0x20
	 */
	

	63'h000: Data = 32'hF84003E9;
	63'h004: Data = 32'hF84083EA;
	63'h008: Data = 32'hF84103EB;
	63'h00c: Data = 32'hF84183EC;
	63'h010: Data = 32'hF84203ED;
	63'h014: Data = 32'hAA0B014A;
	63'h018: Data = 32'h8A0A018C;
	63'h01c: Data = 32'hB400008C;
	63'h020: Data = 32'h8B0901AD;
	63'h024: Data = 32'hCB09018C;
	63'h028: Data = 32'h17FFFFFD;
	63'h02c: Data = 32'hF80203ED;
	63'h030: Data = 32'hF84203ED;  //One last load to place stored value on memdbus for test checking.

	/* Add code for your tests here */
    
			
	default: Data = 32'hXXXXXXXX;
      endcase
   end
endmodule

ECEN-350/Lab9/Part1/NextPCLogic.v
`timescale 1ns / 1ps

module NextPClogic(NextPC, CurrentPC, SignExtImm64, Branch, ALUZero, Uncondbranch); 
       	input [63:0] CurrentPC, SignExtImm64; 
       	input Branch, ALUZero, Uncondbranch; 
       	output reg [63:0] NextPC; 

    always @(*) begin
   	
      if(Uncondbranch || (Branch && ALUZero)) begin
          NextPC  <= CurrentPC + (SignExtImm64 << 2); // jumps to address
       	end

      else begin // branch and Uncondbranch are false
          NextPC <= CurrentPC + 4;
       	end
   	end

endmodule

ECEN-350/Lab9/Part1/design.sv
// Code your design here
`include "SingleCycleControl.v"
`include "SignExtender.v"
`include "ALU.v"
`include "NextPCLogic.v"
`include "RegisterFile.v"
`include "DataMemory.v"
`include "InstructionMemory.v"

//code from SingleCycleProc.v
module singlecycle(
    input resetl,
    input [63:0] startpc,
    output reg [63:0] currentpc,
    output [63:0] dmemout,
    input CLK
);

    // Next PC connections
    wire [63:0] nextpc;       // The next PC, to be updated on clock cycle

    // Instruction Memory connections
    wire [31:0] instruction;  // The current instruction

    // Parts of instruction
    wire [4:0] rd;            // The destination register
    wire [4:0] rm;            // Operand 1
    wire [4:0] rn;            // Operand 2
    wire [10:0] opcode;

    // Control wires
    wire reg2loc;
    wire alusrc;
    wire mem2reg;
    wire regwrite;
    wire memread;
    wire memwrite;
    wire branch;
    wire uncond_branch;
    wire [3:0] aluctrl;
    wire [1:0] signop;

  
    // Register file connections
    wire [63:0] regoutA;     // Output A
    wire [63:0] regoutB;     // Output B
    wire [63:0] Busw;
  
    // ALU connections
    wire [63:0] aluout;
    wire zero;

    // Sign Extender connections
    wire [63:0] extimm;

  
     NextPClogic NextPClogic(
      .NextPC(nextpc),
      .CurrentPC(currentpc),
      .SignExtImm64(extimm),
      .Branch(branch),
      .ALUZero(zero),
      .Uncondbranch(uncond_branch)
    );
  
    // PC update logic
    always @(negedge CLK)
    begin
        if (resetl)
            currentpc <= nextpc;
        else
            currentpc <= startpc;
    end

    // Parts of instruction
    assign rd = instruction[4:0];
    assign rm = instruction[9:5];
    assign rn = reg2loc ? instruction[4:0] : instruction[20:16];
    assign opcode = instruction[31:21];

    InstructionMemory imem(
        .Data(instruction),
        .Address(currentpc)
    );

    control control(
        .reg2loc(reg2loc),
        .alusrc(alusrc),
        .mem2reg(mem2reg),
        .regwrite(regwrite),
        .memread(memread),
        .memwrite(memwrite),
        .branch(branch),
        .uncond_branch(uncond_branch),
        .aluop(aluctrl),
        .signop(signop),
        .opcode(opcode)
    );

    /*
    * Connect the remaining datapath elements below.
    * Do not forget any additional multiplexers that may be required.
    */
  

  
  
    SignExtender SignExtender(
      .BusImm(extimm),
      .Imm26(instruction),
      .Ctrl(signop)
    );
  
 
  	ALU ALU(
      .BusW(aluout),
      .Zero(zero),
      .BusA(regoutA),
      .BusB(alusrc ? extimm : regoutB),
      .ALUCtrl(aluctrl)
    );
  
 
  	RegisterFile RegisterFile(
      .BusA(regoutA),
      .BusB(regoutB), 
      .BusW((mem2reg) ? dmemout : aluout),
      .RA(rm),
      .RB(rn),
      .RW(rd),
      .RegWr(regwrite),
      .Clk(CLK)
    );
  
  
    DataMemory DataMemory(
      .ReadData(dmemout),
      .Address(aluout),
      .WriteData(regoutB),
      .MemoryRead(memread),
      .MemoryWrite(memwrite),
      .Clock(CLK)
    );
 

endmodule

ECEN-350/Lab9/Part1/testbench.sv
// Code your testbench here
// or browse Examples
`timescale 1ns / 1ps

`define STRLEN 32
`define HalfClockPeriod 60
`define ClockPeriod `HalfClockPeriod * 2

module SingleCycleProcTest_v;

    initial
    begin
        $dumpfile("singlecycle.vcd");
        $dumpvars;
    end

    // These tasks are used to check if a given test has passed and
    // confirm that all tests passed.
    task passTest;
        input [63:0] actualOut, expectedOut;
        input [`STRLEN*8:0] testType;
        inout [7:0] 	  passed;

        if(actualOut == expectedOut) begin $display ("%s passed", testType); passed = passed + 1; end
        else $display ("%s failed: 0x%x should be 0x%x", testType, actualOut, expectedOut);
    endtask

    task allPassed;
        input [7:0] passed;
        input [7:0] numTests;

        if(passed == numTests) $display ("All tests passed");
        else $display("Some tests failed: %d of %d passed", passed, numTests);
    endtask

    // Inputs
    reg        CLK;
    reg        Reset_L;
    reg [63:0] startPC;
    reg [7:0]  passed;
    reg [15:0] watchdog;

    // Outputs
    wire [63:0] dMemOut;
    wire [63:0] currentPC;

    // Instantiate the Unit Under Test (UUT)
    singlecycle uut (
        .CLK(CLK),
        .resetl(Reset_L),
        .startpc(startPC),
        .currentpc(currentPC),
        .dmemout(dMemOut)
    );

    initial begin
        // Initialize Inputs
        Reset_L = 1;
        startPC = 0;
        passed = 0;

        // Initialize Watchdog timer
        watchdog = 0;

        // Wait for global reset
        #(1 * `ClockPeriod);

        // Program 1
        #1
        Reset_L = 0; startPC = 0;
        #(1 * `ClockPeriod);
        Reset_L = 1;

        // ***********************************************************
        // This while loop will continue cycling the processor until the
        // PC reaches the final instruction in the first test.  If the
        // program forms an infinite loop, never reaching the end, the
        // watchdog timer will kick in and kill simulation after 64K
        // cycles.
        // ***********************************************************

        while (currentPC < 64'h34)
        begin
           #(1 * `ClockPeriod);
           $display("CurrentPC:%h",currentPC);
        end
        #(1 * `ClockPeriod);	// One more cycle to load the pass code from the DataMemory.
        passTest(dMemOut, 64'hF, "Results of Program 1", passed);

        // ***********************************************************
        // Add your new tests here
        // ***********************************************************

        // Done
      allPassed(passed, 1);   // Be sure to change the one to match
                                // the number of tests you add.
        $finish;
    end

    initial begin
        CLK = 0;
    end

    // The following is correct if clock starts at LOW level at StartTime //
    always begin
        #`HalfClockPeriod CLK = ~CLK;
        #`HalfClockPeriod CLK = ~CLK;
        watchdog = watchdog +1;
    end

    // Kill the simulation if the watchdog hits 64K cycles
    always @*
        if (watchdog == 16'hFF)
        begin
            $display("Watchdog Timer Expired.");
            $finish;
        end


endmodule

ECEN-350/Lab9/Part1/singlecycle.vcd
$date
Tue Nov 24 20:50:21 2020
$end
$version
Riviera-PRO Version 2020.04.130.7729
$end
$timescale
1 ps
$end

$scope module SingleCycleProcTest_v $end
$var wire 64 ! dMemOut [63:0] $end
$var wire 64 " currentPC [63:0] $end
$var reg 1 # CLK $end
$var reg 1 $ Reset_L $end
$var reg 64 % startPC [63:0] $end
$var reg 8 & passed [7:0] $end
$var reg 16 ' watchdog [15:0] $end

$scope module uut $end
$var wire 1 ( resetl $end
$var wire 64 ) startpc [63:0] $end
$var wire 64 ! dmemout [63:0] $end
$var wire 1 * CLK $end
$var wire 64 + nextpc [63:0] $end
$var wire 1 , instruction [31] $end
$var wire 1 - instruction [30] $end
$var wire 1 . instruction [29] $end
$var wire 1 / instruction [28] $end
$var wire 1 0 instruction [27] $end
$var wire 1 1 instruction [26] $end
$var wire 1 2 instruction [25] $end
$var wire 1 3 instruction [24] $end
$var wire 1 4 instruction [23] $end
$var wire 1 5 instruction [22] $end
$var wire 1 6 instruction [21] $end
$var wire 1 7 instruction [20] $end
$var wire 1 8 instruction [19] $end
$var wire 1 9 instruction [18] $end
$var wire 1 : instruction [17] $end
$var wire 1 ; instruction [16] $end
$var wire 1 < instruction [15] $end
$var wire 1 = instruction [14] $end
$var wire 1 > instruction [13] $end
$var wire 1 ? instruction [12] $end
$var wire 1 @ instruction [11] $end
$var wire 1 A instruction [10] $end
$var wire 1 B instruction [9] $end
$var wire 1 C instruction [8] $end
$var wire 1 D instruction [7] $end
$var wire 1 E instruction [6] $end
$var wire 1 F instruction [5] $end
$var wire 1 G instruction [4] $end
$var wire 1 H instruction [3] $end
$var wire 1 I instruction [2] $end
$var wire 1 J instruction [1] $end
$var wire 1 K instruction [0] $end
$var wire 5 L rd [4:0] $end
$var wire 5 M rm [4:0] $end
$var wire 5 N rn [4:0] $end
$var wire 11 O opcode [10:0] $end
$var wire 1 P reg2loc $end
$var wire 1 Q alusrc $end
$var wire 1 R mem2reg $end
$var wire 1 S regwrite $end
$var wire 1 T memread $end
$var wire 1 U memwrite $end
$var wire 1 V branch $end
$var wire 1 W uncond_branch $end
$var wire 4 X aluctrl [3:0] $end
$var wire 2 Y signop [1:0] $end
$var wire 64 Z regoutA [63:0] $end
$var wire 64 [ regoutB [63:0] $end
$var wire 64 \ Busw [63:0] $end
$var wire 64 ] aluout [63:0] $end
$var wire 1 ^ zero $end
$var wire 64 _ extimm [63:0] $end
$var reg 64 ` currentpc [63:0] $end

$scope module NextPClogic $end
$var wire 64 " CurrentPC [63:0] $end
$var wire 64 _ SignExtImm64 [63:0] $end
$var wire 1 V Branch $end
$var wire 1 ^ ALUZero $end
$var wire 1 W Uncondbranch $end
$var reg 64 a NextPC [63:0] $end
$upscope $end


$scope module imem $end
$var wire 64 " Address [63:0] $end
$var reg 32 b Data [31:0] $end
$var parameter 32 c T_rd [31:0] $end
$var parameter 32 d MemSize [31:0] $end
$upscope $end


$scope module control $end
$var wire 11 O opcode [10:0] $end
$var reg 1 e reg2loc $end
$var reg 1 f alusrc $end
$var reg 1 g mem2reg $end
$var reg 1 h regwrite $end
$var reg 1 i memread $end
$var reg 1 j memwrite $end
$var reg 1 k branch $end
$var reg 1 l uncond_branch $end
$var reg 4 m aluop [3:0] $end
$var reg 2 n signop [1:0] $end
$upscope $end


$scope module SignExtender $end
$var wire 1 2 Imm26 [25] $end
$var wire 1 3 Imm26 [24] $end
$var wire 1 4 Imm26 [23] $end
$var wire 1 5 Imm26 [22] $end
$var wire 1 6 Imm26 [21] $end
$var wire 1 7 Imm26 [20] $end
$var wire 1 8 Imm26 [19] $end
$var wire 1 9 Imm26 [18] $end
$var wire 1 : Imm26 [17] $end
$var wire 1 ; Imm26 [16] $end
$var wire 1 < Imm26 [15] $end
$var wire 1 = Imm26 [14] $end
$var wire 1 > Imm26 [13] $end
$var wire 1 ? Imm26 [12] $end
$var wire 1 @ Imm26 [11] $end
$var wire 1 A Imm26 [10] $end
$var wire 1 B Imm26 [9] $end
$var wire 1 C Imm26 [8] $end
$var wire 1 D Imm26 [7] $end
$var wire 1 E Imm26 [6] $end
$var wire 1 F Imm26 [5] $end
$var wire 1 G Imm26 [4] $end
$var wire 1 H Imm26 [3] $end
$var wire 1 I Imm26 [2] $end
$var wire 1 J Imm26 [1] $end
$var wire 1 K Imm26 [0] $end
$var wire 2 Y Ctrl [1:0] $end
$var reg 64 o BusImm [63:0] $end
$var reg 1 p extBit $end
$upscope $end


$scope module ALU $end
$var wire 64 Z BusA [63:0] $end
$var wire 64 q BusB [63:0] $end
$var wire 4 X ALUCtrl [3:0] $end
$var reg 64 r BusW [63:0] $end
$var reg 1 s Zero $end
$upscope $end


$scope module RegisterFile $end
$var wire 64 Z BusA [63:0] $end
$var wire 64 [ BusB [63:0] $end
$var wire 64 t BusW [63:0] $end
$var wire 5 M RA [4:0] $end
$var wire 5 N RB [4:0] $end
$var wire 5 L RW [4:0] $end
$var wire 1 S RegWr $end
$var wire 1 * Clk $end
$upscope $end


$scope module DataMemory $end
$var wire 64 ] Address [63:0] $end
$var wire 64 [ WriteData [63:0] $end
$var wire 1 T MemoryRead $end
$var wire 1 U MemoryWrite $end
$var wire 1 * Clock $end
$var reg 64 u ReadData [63:0] $end

$scope task initset $end
$var reg 64 v addr [63:0] $end
$var reg 64 w data [63:0] $end
$upscope $end

$upscope $end

$upscope $end


$scope task passTest $end
$var reg 64 x actualOut [63:0] $end
$var reg 64 y expectedOut [63:0] $end
$var reg 257 z testType [256:0] $end
$var reg 8 { passed [7:0] $end
$upscope $end


$scope task allPassed $end
$var reg 8 | passed [7:0] $end
$var reg 8 } numTests [7:0] $end
$upscope $end

$upscope $end

$enddefinitions $end
$dumpvars
bx !
bx "
0#
1$
b0 %
b0 &
b0 '
1(
b0 )
0*
bx +
x,
x-
x.
x/
x0
x1
x2
x3
x4
x5
x6
x7
x8
x9
x:
x;
x<
x=
x>
x?
x@
xA
xB
xC
xD
xE
xF
xG
xH
xI
xJ
xK
bx L
bx M
bx N
bx O
xP
xQ
xR
xS
xT
xU
xV
xW
bx X
bx Y
bx Z
bx [
bz \
bx ]
x^
bx _
bx `
bx a
bx b
b10100 c
b101000 d
xe
xf
xg
xh
xi
xj
xk
xl
bx m
bx n
bx o
xp
bx q
bx r
xs
bx t
bx u
b100000 v
b0 w
bx x
bx y
bx z
bx {
bx |
bx }
$end
#60000
1#
1*
#120000
0#
b1 '
0*
#121000
0$
0(
#180000
1#
1*
#240000
0#
b10 '
0*
b0 `
b0 "
b100 a
b100 +
#241000
1$
1(
#244000
b11111000010000000000001111101001 b
1,
1-
1.
1/
10
01
02
03
04
15
06
07
08
09
0:
0;
0<
0=
0>
0?
0@
0A
1B
1C
1D
1E
1F
0G
1H
0I
0J
1K
b11111000010 O
b11111 M
b0x00x N
b1001 L
1f
1g
1h
1i
0j
0k
0l
b10 m
b10 n
b10 Y
b10 X
0W
0V
0U
1T
1S
1R
1Q
0p
b0 o
b0 _
b0 q
#246000
b0 Z
b0 r
b0 ]
1s
1^
#300000
1#
1*
#320000
b1 u
b1 !
b1 t
#360000
0#
b11 '
0*
b100 `
b100 "
b1000 a
b1000 +
#364000
b11111000010000001000001111101010 b
1<
1J
0K
b0x0x0 N
b1010 L
b1000 o
b1000 _
b1000 q
b1000 r
b1000 ]
0s
0^
#420000
1#
1*
#440000
b1010 u
b1010 !
b1010 t
#480000
0#
b100 '
0*
b1000 `
b1000 "
b1100 a
b1100 +
#484000
b11111000010000010000001111101011 b
1;
0<
1K
b0x0x1 N
b1011 L
b10000 o
b10000 _
b10000 q
b10000 r
b10000 ]
#540000
1#
1*
#560000
b101 u
b101 !
b101 t
#600000
0#
b101 '
0*
b1100 `
b1100 "
b10000 a
b10000 +
#604000
b11111000010000011000001111101100 b
1<
1I
0J
0K
b0xx0x N
b1100 L
b11000 o
b11000 _
b11000 q
b11000 r
b11000 ]
#660000
1#
1*
#680000
b111111111011111010100111110111101010110110111110111011111111 u
b111111111011111010100111110111101010110110111110111011111111 !
b111111111011111010100111110111101010110110111110111011111111 t
#720000
0#
b110 '
0*
b10000 `
b10000 "
b10100 a
b10100 +
#724000
b11111000010000100000001111101101 b
1:
0;
0<
1K
b0xxxx N
b1101 L
b100000 o
b100000 _
b100000 q
b100000 r
b100000 ]
#780000
1#
1*
#800000
b0 u
b0 !
b0 t
#840000
0#
b111 '
0*
b10100 `
b10100 "
b11000 a
b11000 +
#844000
b10101010000010110000000101001010 b
0-
0/
12
05
18
1;
0B
0D
0F
0I
1J
0K
b10101010000 O
b1010 M
b101x N
b1010 L
b10110000 o
b10110000 _
b10110000 q
0e
0f
0g
0i
b1 m
bx n
b10110000 r
b10110000 ]
bx Y
b1 X
0T
0R
0Q
0P
b1011 N
bx q
b10110000 t
bx r
bx ]
bx t
#846000
b101 [
b1010 Z
b101 q
b1111 r
b1111 ]
b1111 t
#900000
1#
1*
#960000
0#
b1000 '
0*
b11000 `
b11000 "
b11100 a
b11100 +
#964000
b10001010000010100000000110001100 b
0.
0;
1D
0E
1I
0J
b10001010000 O
b1100 M
b1010 N
b1100 L
b0 m
b0 X
b0 r
b0 ]
b0 t
1s
1^
#966000
b1111 [
b111111111011111010100111110111101010110110111110111011111111 Z
b1111 q
b1111 r
b1111 ]
b1111 t
0s
0^
#1020000
1#
1*
#1080000
0#
b1001 '
0*
b11100 `
b11100 "
b100000 a
b100000 +
#1084000
b10110100000000000000000010001100 b
1.
1/
00
11
02
08
0:
0C
b10110100000 O
b0 N
b100 M
1e
xg
0h
1k
b111 m
b11 n
b11 Y
b111 X
1V
0S
xR
1P
b1100 N
b0xxxx t
b100 o
b100 _
#1086000
bx Z
#1140000
1#
1*
#1200000
0#
b1010 '
0*
b100000 `
b100000 "
b100100 a
b100100 +
#1204000
b10001011000010010000000110101101 b
0.
0/
10
01
12
13
18
1;
1C
1F
1K
b10001011000 O
b1101 M
b1101 N
b1101 L
b100100000001101 o
b100100000001101 _
0e
0g
1h
0k
b10 m
bx n
bx Y
b10 X
0V
1S
0R
0P
b1001 N
b1111 t
bx r
bx ]
bx t
#1206000
b1 [
b0 Z
b1 q
b1 r
b1 ]
b1 t
#1260000
1#
1*
#1320000
0#
b1011 '
0*
b100100 `
b100100 "
b101000 a
b101000 +
#1324000
b11001011000010010000000110001100 b
1-
0F
0K
b11001011000 O
b1100 M
b1100 L
b110 m
b110 X
b1111111111111111111111111111111111111111111111111111111111111111 r
b1111111111111111111111111111111111111111111111111111111111111111 ]
b1111111111111111111111111111111111111111111111111111111111111111 t
#1326000
b1111 Z
b1110 r
b1110 ]
b1110 t
#1380000
1#
1*
#1440000
0#
b1100 '
0*
b101000 `
b101000 "
b101100 a
b101100 +
#1444000
b10111111111111111111111111101 b
0,
0-
1/
00
11
14
15
16
17
19
1:
1<
1=
1>
1?
1@
1A
1B
1E
1F
1G
1K
b10111111 O
b11111 M
b11111 N
b11101 L
xe
xf
xg
0h
xk
1l
bx m
b0 n
b0 Y
bx X
1W
xV
0S
xR
xQ
xP
b111x1 N
b0x00x0000000xx01 q
b0xxx0 t
1p
b1111111111111111111111111111111111111111111111111111111111111101 o
b1111111111111111111111111111111111111111111111111111111111111101 _
bx01 q
b11100 a
b11100 +
#1446000
bx [
b0 Z
bx q
#1500000
1#
1*
#1560000
0#
b1101 '
0*
b11100 `
b11100 "
b10000 a
b10000 +
#1564000
b10110100000000000000000010001100 b
1,
1.
02
03
04
05
06
07
08
09
0:
0;
0<
0=
0>
0?
0@
0A
0B
0C
0E
0F
0G
0K
b10110100000 O
b100 M
b0xx00 N
b1100 L
0p
b10001100 o
b10001100 _
1e
0f
1k
0l
b111 m
b11 n
b1001001100 a
b1001001100 +
b11 Y
b111 X
0W
1V
0Q
1P
b1100 N
b100 o
b100 _
bx r
b100000 a
b100000 +
bx ]
bx t
#1566000
b1110 [
bx Z
b1110 q
b1110 r
b1110 ]
b0xxx0 t
#1620000
1#
1*
#1680000
0#
b1110 '
0*
b100000 `
b100000 "
b100100 a
b100100 +
